formatize/__init__.py
formatize/const.py
formatize/form.py
formatize-1.0.4.dist-info/licenses/LICENSE
formatize-1.0.4.dist-info/METADATA
formatize-1.0.4.dist-info/WHEEL
formatize-1.0.4.dist-info/top_level.txt
formatize-1.0.4.dist-info/RECORD
