Metadata-Version: 2.4
Name: formatize
Version: 1.0.4
Summary: Literp Formatting Lib
Home-page: https://github.com/asinerum/formatize
Author: Asinerum Conlang Project
Author-email: asinerum.com@gmail.com
License: MIT
Classifier: Programming Language :: Python :: 3
Classifier: License :: OSI Approved :: MIT License
Classifier: Operating System :: OS Independent
Requires-Python: >=3.7
License-File: LICENSE
Requires-Dist: bs4>=0.0.2
Requires-Dist: dnspython>=2.8.0
Requires-Dist: numpy>=2.3.5
Requires-Dist: pandas>=2.3.3
Requires-Dist: pillow>=12.0.0
Requires-Dist: pydantic>=2.12.5
Requires-Dist: pyyaml>=6.0.3
Requires-Dist: typing-extensions>=4.15.0
Dynamic: license-file
